setup.py
sunny_day_forecast/__init__.py
sunny_day_forecast/sunny_day_forecast.py
sunny_day_forecast.egg-info/PKG-INFO
sunny_day_forecast.egg-info/SOURCES.txt
sunny_day_forecast.egg-info/dependency_links.txt
sunny_day_forecast.egg-info/requires.txt
sunny_day_forecast.egg-info/top_level.txt